whassup/__init__.py
whassup/exceptions.py
whassup-0.12.0.data/scripts/whassup
whassup-0.12.0.dist-info/LICENSE
whassup-0.12.0.dist-info/METADATA
whassup-0.12.0.dist-info/WHEEL
whassup-0.12.0.dist-info/top_level.txt
whassup-0.12.0.dist-info/RECORD
