Metadata-Version: 2.1
Name: whassup
Version: 0.12.0
Summary: Minimalist health-check for stayinalive
Home-page: https://zebr0.io/projects/whassup
Download-URL: https://gitlab.com/zebr0/whassup
Author: Thomas JOUANNOT
Author-email: mazerty@gmail.com
License: MIT
Classifier: Development Status :: 4 - Beta
Classifier: Environment :: Console
Classifier: Intended Audience :: Developers
Classifier: Intended Audience :: Information Technology
Classifier: Intended Audience :: System Administrators
Classifier: License :: OSI Approved :: MIT License
Classifier: Natural Language :: English
Classifier: Operating System :: POSIX
Classifier: Programming Language :: Python :: 3
Classifier: Topic :: System
License-File: LICENSE
Requires-Dist: requests
